sparkit/__init__.py
sparkit/exception.py
sparkit/pandastools.py
sparkit/transformation.py
sparkit/validation.py
sparkit-1.1.1.dist-info/LICENSE
sparkit-1.1.1.dist-info/WHEEL
sparkit-1.1.1.dist-info/METADATA
sparkit-1.1.1.dist-info/RECORD
