Metadata-Version: 2.1
Name: sparkit
Version: 1.1.1
Summary: A package for PySpark utility functions.
Home-page: https://github.com/estripling/sparkit
License: BSD 3-Clause
Keywords: sparkit
Author: sparkit Developers
Requires-Python: >=3.8,<4.0
Classifier: License :: Other/Proprietary License
Classifier: Programming Language :: Python :: 3
Classifier: Programming Language :: Python :: 3.8
Classifier: Programming Language :: Python :: 3.9
Classifier: Programming Language :: Python :: 3.10
Classifier: Programming Language :: Python :: 3.11
Classifier: Programming Language :: Python :: 3
Requires-Dist: bumbag (>=5.2.1,<6.0.0)
Requires-Dist: pandas (>=1.5.3,<2.0.0)
Requires-Dist: pyarrow (>=11.0.0,<12.0.0)
Requires-Dist: pyspark (>=3,<4)
Project-URL: Documentation, https://sparkit.readthedocs.io/en/stable/
Project-URL: Repository, https://github.com/estripling/sparkit
